graphmytunes-1.0.0.dist-info/licenses/LICENSE
src/__init__.py
src/main.py
src/analysis/__init__.py
src/analysis/_utils_.py
src/analysis/album_avg_daily_plays.py
src/analysis/album_avg_rating.py
src/analysis/album_plays.py
src/analysis/album_playtime.py
src/analysis/album_skips.py
src/analysis/artist_avg_daily_plays.py
src/analysis/artist_avg_rating.py
src/analysis/artist_plays.py
src/analysis/artist_playtime.py
src/analysis/artist_skips.py
src/analysis/bitrate_distribution.py
src/analysis/bpm_plays.py
src/analysis/bpm_tracks.py
src/analysis/decade_plays.py
src/analysis/decade_playtime.py
src/analysis/decade_tracks.py
src/analysis/duration_distribution.py
src/analysis/genre_avg_rating.py
src/analysis/genre_plays.py
src/analysis/genre_playtime.py
src/analysis/genre_tracks_bar.py
src/analysis/genre_tracks_pie.py
src/analysis/historical_date_added.py
src/analysis/historical_last_played.py
src/analysis/historical_library_plays.py
src/analysis/historical_library_size.py
src/analysis/historical_library_tracks.py
src/analysis/historical_play_counts.py
src/analysis/historical_playtime.py
src/analysis/kind_distribution.py
src/analysis/library_overview.py
src/analysis/play_count_distribution.py
src/analysis/plays_by_hour.py
src/analysis/plays_by_isoweek.py
src/analysis/plays_by_month.py
src/analysis/plays_by_weekday.py
src/analysis/playtime_by_hour.py
src/analysis/playtime_by_isoweek.py
src/analysis/playtime_by_month.py
src/analysis/playtime_by_weekday.py
src/analysis/rating_plays.py
src/analysis/rating_tracks.py
src/analysis/track_avg_daily_plays.py
src/analysis/yearly_songs_by_plays.py
src/analysis/yearly_songs_by_playtime.py
graphmytunes-1.0.0.dist-info/METADATA
graphmytunes-1.0.0.dist-info/WHEEL
graphmytunes-1.0.0.dist-info/entry_points.txt
graphmytunes-1.0.0.dist-info/top_level.txt
graphmytunes-1.0.0.dist-info/RECORD
