Metadata-Version: 2.4
Name: GraphMyTunes
Version: 1.0.0
Summary: Apple Music library analysis and visualization tool
Author-email: Elliot Jordan <GraphMyTunes@elliotjordan.com>
License: 
Project-URL: Homepage, https://github.com/homebysix/GraphMyTunes
Project-URL: Repository, https://github.com/homebysix/GraphMyTunes
Project-URL: Issues, https://github.com/homebysix/GraphMyTunes/issues
Requires-Python: >=3.9
License-File: LICENSE
Requires-Dist: pandas
Requires-Dist: matplotlib
Requires-Dist: pyyaml
Dynamic: license-file
